.gitignore
LICENSE
README.rst
__init__.py
setup.py
xlearning/__init__.py
xlearning/version.py
xlearning.egg-info/PKG-INFO
xlearning.egg-info/SOURCES.txt
xlearning.egg-info/dependency_links.txt
xlearning.egg-info/requires.txt
xlearning.egg-info/top_level.txt
xlearning/plot/RT_visualization.py
xlearning/plot/__init__.py